__init__.py
ninetydf/__init__.py
ninetydf/couples.csv
ninetydf/csv_loader.py
ninetydf/df_loader.py
ninetydf/models.py
ninetydf/seasons.csv
ninetydf-0.7.1.dist-info/LICENSE.txt
ninetydf-0.7.1.dist-info/METADATA
ninetydf-0.7.1.dist-info/WHEEL
ninetydf-0.7.1.dist-info/top_level.txt
ninetydf-0.7.1.dist-info/RECORD
