Metadata-Version: 2.1
Name: ninetydf
Version: 0.7.1
Summary: 90 Day Fiancé DataFrames
Author: 90df
License: MIT
Project-URL: repository, https://github.com/90df/ninetydf
Classifier: Intended Audience :: Science/Research
Classifier: Topic :: Scientific/Engineering
Classifier: Programming Language :: Python :: 3.7
Classifier: Programming Language :: Python :: 3.8
Classifier: Programming Language :: Python :: 3.9
Classifier: Programming Language :: Python :: 3.10
Classifier: Programming Language :: Python :: 3.11
License-File: LICENSE.txt
Requires-Dist: importlib-resources ; python_version < "3.9"
Provides-Extra: dev
Requires-Dist: pytest ==7.4.2 ; extra == 'dev'
Requires-Dist: black ==23.9.1 ; extra == 'dev'
Provides-Extra: pandas
Requires-Dist: pandas ; extra == 'pandas'
